pink/__init__.py
pink/cnrl.py
pink/colorednoise.py
pink/sb3.py
pink/tonic.py
pink_noise_rl-2.0.0.dist-info/LICENSE
pink_noise_rl-2.0.0.dist-info/WHEEL
pink_noise_rl-2.0.0.dist-info/METADATA
pink_noise_rl-2.0.0.dist-info/RECORD
