Metadata-Version: 2.1
Name: pink-noise-rl
Version: 2.0.0
Summary: Pink noise for exploration in reinforcement learning
Home-page: https://github.com/martius-lab/pink-noise-rl
License: MIT
Author: Onno Eberhard
Author-email: onnoeberhard@gmail.com
Requires-Python: >=3.8,<4.0
Classifier: License :: OSI Approved :: MIT License
Classifier: Programming Language :: Python :: 3
Classifier: Programming Language :: Python :: 3.8
Classifier: Programming Language :: Python :: 3.9
Classifier: Programming Language :: Python :: 3.10
Classifier: Programming Language :: Python :: 3.11
Requires-Dist: numpy
Project-URL: Repository, https://github.com/martius-lab/pink-noise-rl
